aioampio/__init__.py
aioampio/bridge.py
aioampio/cli.py
aioampio/config.py
aioampio/state_store.py
aioampio/util.py
aioampio/codec/__init__.py
aioampio/codec/ampio.py
aioampio/codec/base.py
aioampio/codec/helper.py
aioampio/codec/registry.py
aioampio/codec/spec.py
aioampio/controllers/__init__.py
aioampio/controllers/alarm_control_panels.py
aioampio/controllers/areas.py
aioampio/controllers/base.py
aioampio/controllers/binary_sensors.py
aioampio/controllers/climates.py
aioampio/controllers/covers.py
aioampio/controllers/devices.py
aioampio/controllers/events.py
aioampio/controllers/floors.py
aioampio/controllers/lights.py
aioampio/controllers/metrics.py
aioampio/controllers/sensors.py
aioampio/controllers/switches.py
aioampio/controllers/texts.py
aioampio/controllers/utils.py
aioampio/controllers/valves.py
aioampio/helpers/__init__.py
aioampio/helpers/rx_reader.py
aioampio/models/__init__.py
aioampio/models/alarm_control_panel.py
aioampio/models/area.py
aioampio/models/binary_sensor.py
aioampio/models/climate.py
aioampio/models/config.py
aioampio/models/cover.py
aioampio/models/device.py
aioampio/models/feature.py
aioampio/models/floor.py
aioampio/models/light.py
aioampio/models/resource.py
aioampio/models/sensor.py
aioampio/models/switch.py
aioampio/models/text.py
aioampio/models/valve.py
aioampio-1.0.0.dist-info/licenses/LICENSE
aioampio-1.0.0.dist-info/METADATA
aioampio-1.0.0.dist-info/WHEEL
aioampio-1.0.0.dist-info/entry_points.txt
aioampio-1.0.0.dist-info/top_level.txt
aioampio-1.0.0.dist-info/RECORD
